pyfb_kamailio/__init__.py
pyfb_kamailio/admin.py
pyfb_kamailio/api.py
pyfb_kamailio/apps.py
pyfb_kamailio/forms.py
pyfb_kamailio/models.py
pyfb_kamailio/serializers.py
pyfb_kamailio/urls.py
pyfb_kamailio/views.py
pyfb_kamailio/migrations/0001_initial.py
pyfb_kamailio/migrations/0002_auto_20190130_1634.py
pyfb_kamailio/migrations/0003_auto_20190130_1708.py
pyfb_kamailio/migrations/0004_auto_20190225_1140.py
pyfb_kamailio/migrations/0005_auto_20190225_1803.py
pyfb_kamailio/migrations/0006_toposd_topost.py
pyfb_kamailio/migrations/0007_auto_20190306_1514.py
pyfb_kamailio/migrations/0008_auto_20190523_1635.py
pyfb_kamailio/migrations/0009_auto_20190523_1647.py
pyfb_kamailio/migrations/0010_auto_20200321_1551.py
pyfb_kamailio/migrations/0011_auto_20200514_1000.py
pyfb_kamailio/migrations/0012_auto_20200514_1705.py
pyfb_kamailio/migrations/0013_auto_20200514_1707.py
pyfb_kamailio/migrations/0014_auto_20200518_1647.py
pyfb_kamailio/migrations/0015_acccdr_cdr_id.py
pyfb_kamailio/migrations/0016_auto_20200527_0751.py
pyfb_kamailio/migrations/__init__.py
pyfb_kamailio/static/css/pyfb_kamailio.css
pyfb_kamailio/static/js/pyfb_kamailio.js
pyfb_kamailio/templates/base.html
pyfb_kamailio/templates/base.html.py
pyfb_kamailio/templates/pyfb_kamailio/acc_detail.html
pyfb_kamailio/templates/pyfb_kamailio/acc_detail.html.py
pyfb_kamailio/templates/pyfb_kamailio/acc_form.html
pyfb_kamailio/templates/pyfb_kamailio/acc_form.html.py
pyfb_kamailio/templates/pyfb_kamailio/acc_list.html
pyfb_kamailio/templates/pyfb_kamailio/acc_list.html.py
pyfb_kamailio/templates/pyfb_kamailio/acccdr_detail.html
pyfb_kamailio/templates/pyfb_kamailio/acccdr_detail.html.py
pyfb_kamailio/templates/pyfb_kamailio/acccdr_form.html
pyfb_kamailio/templates/pyfb_kamailio/acccdr_form.html.py
pyfb_kamailio/templates/pyfb_kamailio/acccdr_list.html
pyfb_kamailio/templates/pyfb_kamailio/acccdr_list.html.py
pyfb_kamailio/templates/pyfb_kamailio/dialog_detail.html
pyfb_kamailio-1.2.2.dist-info/AUTHORS.rst
pyfb_kamailio-1.2.2.dist-info/LICENSE
pyfb_kamailio-1.2.2.dist-info/METADATA
pyfb_kamailio-1.2.2.dist-info/SOURCES.txt.py
pyfb_kamailio-1.2.2.dist-info/WHEEL
pyfb_kamailio-1.2.2.dist-info/dependency_links.txt.py
pyfb_kamailio-1.2.2.dist-info/requires.txt.py
pyfb_kamailio-1.2.2.dist-info/top_level.txt
pyfb_kamailio-1.2.2.dist-info/top_level.txt.py
pyfb_kamailio-1.2.2.dist-info/RECORD
